README.md
setup.cfg
setup.py
seams/__init__.py
seams/exceptions.py
seams/pipeline.py
seams/seams.py
seams/severity.py
seams.egg-info/PKG-INFO
seams.egg-info/SOURCES.txt
seams.egg-info/dependency_links.txt
seams.egg-info/requires.txt
seams.egg-info/top_level.txt