Metadata-Version: 2.1
Name: seams
Version: 0.1.57
Summary: A python SDK for the Seams API
Home-page: https://github.com/user/reponame
Author: David Bickford
Author-email: dbickford@rjleegroup.com
License: UNKNOWN
Download-URL: https://github.com/user/reponame/archive/v_01.tar.gz
Keywords: seams,seam,rjlg,rjleegroup,rjlee,rj lee group,rj lee
Platform: UNKNOWN
Classifier: Development Status :: 3 - Alpha
Classifier: Intended Audience :: Developers
Classifier: Topic :: Software Development :: Build Tools
Classifier: License :: OSI Approved :: MIT License
Classifier: Programming Language :: Python :: 3
Classifier: Programming Language :: Python :: 3.4
Classifier: Programming Language :: Python :: 3.5
Classifier: Programming Language :: Python :: 3.6
Classifier: Programming Language :: Python :: 3.7
Classifier: Programming Language :: Python :: 3.8
Classifier: Programming Language :: Python :: 3.9
Classifier: Programming Language :: Python :: 3.10
